maskrcnn_utils
