Metadata-Version: 1.0
Name: maskrcnn-utils
Version: 0.1.5
Summary: this is a tool package for maskrcnn
Home-page: https://github.com/iHateTa11B0y/CROIUtils
Author: Kuuuurt
Author-email: niu1187203155@gmail.com
License: UNKNOWN
Platform: UNKNOWN
